LICENSE
apos/__init__.py
apos/core.py
apos/exceptions.py
apos/interfaces.py
apos-0.2.1.2.dist-info/LICENSE
apos-0.2.1.2.dist-info/WHEEL
apos-0.2.1.2.dist-info/METADATA
apos-0.2.1.2.dist-info/RECORD
